tarchia/__init__.py
tarchia/__version__.py
tarchia/config.py
tarchia/constants.py
tarchia/debugging.py
tarchia/exceptions.py
tarchia/main.py
tarchia/compaction/__init__.py
tarchia/manifests/__init__.py
tarchia/manifests/models.py
tarchia/manifests/pruning.py
tarchia/middlewares/__init__.py
tarchia/middlewares/audit_middleware.py
tarchia/middlewares/authorization_middleware.py
tarchia/models/__init__.py
tarchia/models/metadata_models.py
tarchia/models/request_models.py
tarchia/models/tarchia_base.py
tarchia/repositories/__init__.py
tarchia/repositories/catalog/__init__.py
tarchia/repositories/catalog/dev_catalog.py
tarchia/repositories/catalog/gcs_firestore.py
tarchia/repositories/catalog/provider_base.py
tarchia/storage/__init__.py
tarchia/storage/google_cloud_storage.py
tarchia/storage/local_storage.py
tarchia/storage/s3_storage.py
tarchia/storage/storage_provider.py
tarchia/utils/__init__.py
tarchia/utils/catalog.py
tarchia/utils/dnf_filters.py
tarchia/utils/doc_store.py
tarchia/utils/profiler.py
tarchia/utils/serde.py
tarchia/v1/__init__.py
tarchia/v1/routes/__init__.py
tarchia/v1/routes/authorization.py
tarchia/v1/routes/data_management.py
tarchia/v1/routes/maintenance.py
tarchia/v1/routes/owner_management.py
tarchia/v1/routes/schema_management.py
tarchia/v1/routes/table_management.py
tarchia-0.0.0.dist-info/LICENSE
tarchia-0.0.0.dist-info/METADATA
tarchia-0.0.0.dist-info/WHEEL
tarchia-0.0.0.dist-info/top_level.txt
tarchia-0.0.0.dist-info/RECORD
