Metadata-Version: 2.1
Name: tarchia
Version: 0.0.0
Summary: Tarchia - Metadata Catalog
Home-page: https://github.com/mabel-dev/{LIBRARY}/
Author: notset
Author-email: justin.joyce@joocer.com
Maintainer: @joocer
Requires-Python: >=3.9
License-File: LICENSE
Requires-Dist: cityhash
Requires-Dist: fastapi
Requires-Dist: fastavro
Requires-Dist: numpy ==1.*
Requires-Dist: orjson
Requires-Dist: orso
Requires-Dist: pyarrow
Requires-Dist: pydantic
